arkfast/__init__.py
arkfast/utils.py
arkfast-0.2.0.dist-info/WHEEL
arkfast-0.2.0.dist-info/METADATA
arkfast-0.2.0.dist-info/RECORD
