Metadata-Version: 2.3
Name: arkfast
Version: 0.2.0
Summary: Utilities for faster POC development.
Keywords: arkfast
Author: Arkadiusz Michał Ryś
Author-email: Arkadiusz Michał Ryś <Arkadiusz.Michal.Rys@gmail.com>
License: MIT License
Classifier: Development Status :: 2 - Pre-Alpha
Classifier: Intended Audience :: Developers
Classifier: Natural Language :: English
Classifier: Programming Language :: Python :: 3
Requires-Dist: toml>=0.10.2,<1
Requires-Python: >=3.14
Project-URL: source, https://git.rys.one/arrys/arkfast
Provides-Extra: gui
